.gitignore
.stickler.yml
.travis.yml
setup.py
tox.ini
.github/main.workflow
docs/README.md
pbsmonitor/__init__.py
pbsmonitor/_commandline.py
pbsmonitor/monitor.py
pbsmonitor.egg-info/PKG-INFO
pbsmonitor.egg-info/SOURCES.txt
pbsmonitor.egg-info/dependency_links.txt
pbsmonitor.egg-info/entry_points.txt
pbsmonitor.egg-info/requires.txt
pbsmonitor.egg-info/top_level.txt
pbsmonitor.egg-info/zip-safe
pbsmonitor/bots/__init__.py
pbsmonitor/bots/bot.py
pbsmonitor/bots/qqbot.py
pbsmonitor/tests/__init__.py
pbsmonitor/tests/test_monitor.py