Metadata-Version: 2.1
Name: pbsmonitor
Version: 1.0.6
Summary: A PBS job monitor powered by CoolQ.
Home-page: https://github.com/njzjz/pbsmonitor
Author: Jinzhe Zeng
Author-email: jzzeng@stu.ecnu.edu.cn
License: UNKNOWN
Keywords: ecnu
Platform: UNKNOWN
Classifier: Natural Language :: English
Classifier: Operating System :: POSIX :: Linux
Classifier: Programming Language :: Python :: 3.6
Classifier: Programming Language :: Python :: 3.7
Classifier: Topic :: Software Development :: Libraries :: Python Modules
Classifier: Topic :: Software Development :: Version Control :: Git
Provides-Extra: test
